{"is_source_file": true, "format": "JavaScript (React)", "description": "This file is the entry point for a React-based frontend application, initializing and rendering the root React component into the DOM.", "external_files": ["react", "react-dom/client", "./index.css", "./App"], "external_methods": ["ReactDOM.createRoot", "ReactDOM.render", "React.StrictMode"], "published": ["React"], "classes": [], "methods": [{"name": "ReactDOM.createRoot", "description": "Creates a root for rendering React components into the DOM."}, {"name": "root.render", "description": "Renders the React component tree into the DOM."}], "calls": ["ReactDOM.createRoot", "root.render", "React.StrictMode", "App"], "search-terms": ["React", "ReactDOM", "entry point", "index.js", "frontend initialization", "React StrictMode"], "state": 2, "file_id": 4, "knowledge_revision": 23, "git_revision": "738fd55627ed3168e4de959c2a1a6d1968584cd2", "ctags": [{"_type": "tag", "name": "root", "path": "/home/kavia/workspace/code-generation/online-shopping-platform-25724-25743/ecommerce_frontend/src/index.js", "pattern": "/^const root = ReactDOM.createRoot(document.getElementById('root'));$/", "language": "JavaScript", "kind": "constant"}], "hash": "9fc5841375336fc175b49f8767a11383", "format-version": 4, "code-base-name": "ecommerce_frontend", "filename": "ecommerce_frontend/src/index.js", "revision_history": [{"23": "738fd55627ed3168e4de959c2a1a6d1968584cd2"}]}